mcpauth/__init__.py
mcpauth/config.py
mcpauth/exceptions.py
mcpauth/types.py
mcpauth/middleware/create_bearer_auth.py
mcpauth/utils/__init__.py
mcpauth/utils/_create_verify_jwt.py
mcpauth/utils/_fetch_server_config.py
mcpauth/utils/_validate_server_config.py
mcpauth-0.1.0.dist-info/licenses/LICENSE
mcpauth-0.1.0.dist-info/METADATA
mcpauth-0.1.0.dist-info/WHEEL
mcpauth-0.1.0.dist-info/top_level.txt
mcpauth-0.1.0.dist-info/RECORD
