Metadata-Version: 2.4
Name: mcpauth
Version: 0.1.0
Summary: Plug-and-play auth for Python MCP servers.
Author-email: "Silverhand Inc." <contact@silverhand.io>
License-Expression: MIT
Project-URL: homepage, https://mcp-auth.dev
Project-URL: repository, https://github.com/mcp-auth/python
Project-URL: documentation, https://mcp-auth.dev/docs
Keywords: authentication,authorization,mcp,modelcontextprotocol,oauth2,openid-connect,oidc
Requires-Python: <4.0,>=3.10
License-File: LICENSE
Requires-Dist: pydantic>=2.11.3
Requires-Dist: pyjwt[crypto]>=2.9.0
Requires-Dist: requests>=2.32.3
Requires-Dist: starlette>=0.46.2
Dynamic: license-file
